cricpy/__init__.py
cricpy/analytics.py
cricpy-0.0.25.10.dist-info/LICENSE.txt
cricpy-0.0.25.10.dist-info/METADATA
cricpy-0.0.25.10.dist-info/WHEEL
cricpy-0.0.25.10.dist-info/top_level.txt
cricpy-0.0.25.10.dist-info/RECORD
