Metadata-Version: 2.1
Name: cricpy
Version: 0.0.25.10
Summary: Analyze Cricketers Based on ESPN Cricinfo Statsguru
Home-page: https://github.com/tvganesh/cricpy
Author: Tinniam V Ganesh
Author-email: tvganesh.85@gmail.com
Classifier: Programming Language :: Python :: 3
Classifier: License :: OSI Approved :: MIT License
Classifier: Operating System :: OS Independent
License-File: LICENSE.txt
